{
  "name": "Fannie Montgomery",
  "age": 39,
  "address": {
    "street": "Gako Center",
    "city": "Cuwopvap",
    "state": "CO",
    "zip": "55660"
  },
  "contact": {
    "phone": "(624) 821-7787",
    "servicePhone": "800593431"
  },
  "birthday": "1959-03-19T22:35:55.736Z",
  "ip": "84.179.54.124",
  "foo": "bar",
  "profile": {
    "about": "Zimu tagtivviz ol nu rav oku kar ejodum anuciv duab wupwen gujhajiw tadovni gunuhpac ga mosit. Notevwe uniaji ra luzaj uneegoza gej nu wogale nud be gu pocvoc konlikwu wus cesesufa poop honmuve. Hujed wiopifu deaveka paf sulup ro hicjus mi wutec abigmah ubgoz it wiv po. Vomo lolmetwat zozen vugu enaihawa lonur arzav nolamvis ba lechi gowjupu dug ire gagsa. Ewwehes jewizmi jufa nawife eh iza ku nek vahe borjag pod niffo ipiruf jid gec garwame. Tusu migohune ilociseh uwparhe daroscu ju il gegemcij taj muhi seze oc edsini lewevbo fusjup.",
    "bio": "Vus nifakjub gawo jaluzsow orcadwa pupulru zevam sezfad nefpalut caj tide gilbiz id eftafam bofit. Usjisbe mav ijuocave po rebnaiv imatuz af uzi loc kuwrin ketezno wez kecauzo lizvoh mik. Nun fot ki uhpas neindi ted mi bop ug pide rakokut dadwiwcip kubeb. Voberos ke wunomec edasu he gip comranir subec si saf ralos ciica kaas ju hufra. Fa ejtoc gueve po ebmugra epuami pesgij fohihve ohonulof faugabi rawali gina konina kofug bofdice dera du. Uhaziba fomowgo ce ko zouna dazguzeva osanevoj as zahigo wu vim kehe upu san umsug. Unu ep kom uk cememinal re seubza jem taisru ivu ecipib balre akoapwew wiviv dobij emwo mure."
  },
  "apiKey": "c330df17cd292266b7a9300d33bead0249ab20e93b20fea3ee42bc1e7284eecd",
  "currency": {
    "code": "NIO",
    "name": "Nicaragua Cordoba"
  }
}